llama_tokens/__init__.py
llama_tokens/main_module.py
llama_tokens-0.0.3.dist-info/LICENSE
llama_tokens-0.0.3.dist-info/METADATA
llama_tokens-0.0.3.dist-info/WHEEL
llama_tokens-0.0.3.dist-info/top_level.txt
llama_tokens-0.0.3.dist-info/RECORD
